princo/__init__.py
princo/princo.py
princo-5.1.5.dist-info/LICENSE.txt
princo-5.1.5.dist-info/METADATA
princo-5.1.5.dist-info/WHEEL
princo-5.1.5.dist-info/top_level.txt
princo-5.1.5.dist-info/RECORD
