Metadata-Version: 2.1
Name: princo
Version: 5.1.5
Summary: princo package
Author: The Urban Penguin
Author-email: mahdisahnoun31@gmail.com
License-File: LICENSE.txt
